setup.py
zebra_print.py
zebra_printer.egg-info/PKG-INFO
zebra_printer.egg-info/SOURCES.txt
zebra_printer.egg-info/dependency_links.txt
zebra_printer.egg-info/requires.txt
zebra_printer.egg-info/top_level.txt