Metadata-Version: 1.0
Name: zebra-printer
Version: 1.0.0
Summary: a tool for zebra printer
Home-page: https://github.com/hanchuanjun/zebra-print-service
Author: shock1974
Author-email: han@inhand.com.cn
License: MIT
Platform: UNKNOWN
